MANIFEST.in
README
setup.py
api_auth/__init__.py
api_auth/admin.py
api_auth/authentication.py
api_auth/authentication2.py
api_auth/models.py
api_auth/signals.py
api_auth/tests.py
api_auth/utils.py
api_auth/views.py
api_auth/management/__init__.py
api_auth/management/commands/__init__.py
api_auth/management/commands/delete_old_nonces.py
piston_api_auth.egg-info/PKG-INFO
piston_api_auth.egg-info/SOURCES.txt
piston_api_auth.egg-info/dependency_links.txt
piston_api_auth.egg-info/not-zip-safe
piston_api_auth.egg-info/top_level.txt