Metadata-Version: 1.0
Name: piston-api-auth
Version: 0.1.1
Summary: Piston authentication extension that adds per request signing (similar with 2 legged OAuth).
Home-page: https://bitbucket.org/severb/piston-api-auth
Author: Sever Banesiu
Author-email: banesiu.sever@gmail.com
License: BSD
Platform: UNKNOWN
Classifier: Development Status :: 3 - Alpha
Classifier: Framework :: Django
Classifier: Intended Audience :: Developers
Classifier: License :: OSI Approved :: BSD License
Classifier: Operating System :: OS Independent
Classifier: Programming Language :: Python
Classifier: Topic :: Internet :: WWW/HTTP
